MANIFEST.in
README.rst
pylot-runner.py
setup.py
pylot_dojo.egg-info/PKG-INFO
pylot_dojo.egg-info/SOURCES.txt
pylot_dojo.egg-info/dependency_links.txt
pylot_dojo.egg-info/entry_points.txt
pylot_dojo.egg-info/top_level.txt
src/__init__.py
src/__main__.py
src/pylot.py
src/Pylot/__init__.py
src/Pylot/manage.py
src/Pylot/wsgi.py
src/Pylot/app/__init__.py
src/Pylot/app/config/__init__.py
src/Pylot/app/config/base.py
src/Pylot/app/config/database.py
src/Pylot/app/config/routes.py
src/Pylot/app/controllers/Welcome.py
src/Pylot/app/controllers/__init__.py
src/Pylot/app/models/WelcomeModel.py
src/Pylot/app/models/__init__.py
src/Pylot/system/__init__.py
src/Pylot/system/core/__init__.py
src/Pylot/system/core/controller.py
src/Pylot/system/core/model.py
src/Pylot/system/core/router.py
src/Pylot/system/db/__init__.py
src/Pylot/system/db/db_init.py
src/Pylot/system/db/drivers/__init__.py
src/Pylot/system/db/drivers/_mysql.py
src/Pylot/system/init/__init__.py
src/Pylot/system/init/configuration.py
src/Pylot/system/init/database.py
src/Pylot/system/init/routes.py