Metadata-Version: 1.0
Name: pylot-dojo
Version: 0.1.0
Summary: MVC framework build on top of flask
Home-page: https://github.com/Ketul-Patel/Pylot
Author: Ketul Patel, Jimmy Jun, Oscar Vazquez, Pariece Mckinney
Author-email: UNKNOWN
License: UNKNOWN
Platform: UNKNOWN
